README.md
setup.py
hpbandster/__init__.py
hpbandster/utils.py
hpbandster/visualization.py
hpbandster.egg-info/PKG-INFO
hpbandster.egg-info/SOURCES.txt
hpbandster.egg-info/dependency_links.txt
hpbandster.egg-info/requires.txt
hpbandster.egg-info/top_level.txt
hpbandster/core/__init__.py
hpbandster/core/base_config_generator.py
hpbandster/core/base_iteration.py
hpbandster/core/dispatcher.py
hpbandster/core/master.py
hpbandster/core/nameserver.py
hpbandster/core/result.py
hpbandster/core/worker.py
hpbandster/examples/__init__.py
hpbandster/examples/commons.py
hpbandster/examples/example_1_local_sequential.py
hpbandster/examples/example_2_local_parallel_threads.py
hpbandster/examples/example_3_local_parallel_processes.py
hpbandster/examples/example_4_cluster.py
hpbandster/examples/example_5_keras_worker.py
hpbandster/examples/example_5_mnist.py
hpbandster/examples/example_5_pytorch_worker.py
hpbandster/examples/example_8_mnist_continued.py
hpbandster/examples/plot_example_6_analysis.py
hpbandster/examples/plot_example_7_interactive_plot.py
hpbandster/optimizers/__init__.py
hpbandster/optimizers/bohb.py
hpbandster/optimizers/h2bo.py
hpbandster/optimizers/hyperband.py
hpbandster/optimizers/lcnet.py
hpbandster/optimizers/randomsearch.py
hpbandster/optimizers/config_generators/__init__.py
hpbandster/optimizers/config_generators/bohb.py
hpbandster/optimizers/config_generators/h2bo.py
hpbandster/optimizers/config_generators/kde.py
hpbandster/optimizers/config_generators/lcnet.py
hpbandster/optimizers/config_generators/random_sampling.py
hpbandster/optimizers/iterations/__init__.py
hpbandster/optimizers/iterations/successivehalving.py
hpbandster/optimizers/iterations/successiveresampling.py
hpbandster/optimizers/kde/__init__.py
hpbandster/optimizers/kde/kernels.py
hpbandster/optimizers/kde/mvkde.py
hpbandster/optimizers/learning_curve_models/__init__.py
hpbandster/optimizers/learning_curve_models/arif.py
hpbandster/optimizers/learning_curve_models/base.py
hpbandster/optimizers/learning_curve_models/lcnet.py
hpbandster/workers/__init__.py
hpbandster/workers/hpolibbenchmark.py